aptiviti_survey_utilities/__init__.py
aptiviti_survey_utilities-1.0.6.dist-info/METADATA
aptiviti_survey_utilities-1.0.6.dist-info/WHEEL
aptiviti_survey_utilities-1.0.6.dist-info/top_level.txt
aptiviti_survey_utilities-1.0.6.dist-info/RECORD
