Metadata-Version: 2.1
Name: aptiviti-survey-utilities
Version: 1.0.6
Summary: Useful helper functions for accessing ETR TSIS data
Home-page: https://github.com/aptiviti/aptiviti_survey_utilities
Author: Daniel Fredriksen
Author-email: df@etr.ai
License: AGPLv3
Platform: UNKNOWN
